llm_execution_time_predictor/__init__.py
llm_execution_time_predictor/batch_benchmark_runner.py
llm_execution_time_predictor/bench_backend_handler.py
llm_execution_time_predictor/bench_utils.py
llm_execution_time_predictor/llm_forward_predictor_cli.py
llm_execution_time_predictor/llm_predictor_viewer.py
llm_execution_time_predictor/sglang_batch_latency.py
llm_execution_time_predictor/train_utils.py
llm_execution_time_predictor/vllm_batch_latency.py
llm_execution_time_predictor-0.1.2.dist-info/licenses/LICENSE
llm_execution_time_predictor-0.1.2.dist-info/METADATA
llm_execution_time_predictor-0.1.2.dist-info/WHEEL
llm_execution_time_predictor-0.1.2.dist-info/entry_points.txt
llm_execution_time_predictor-0.1.2.dist-info/top_level.txt
llm_execution_time_predictor-0.1.2.dist-info/RECORD
