Metadata-Version: 2.4
Name: llm_execution_time_predictor
Version: 0.1.2
Summary: LLM batch inference latency predictor and profiler CLI tool
Author-email: Vikranth Srivatsa <vsrivatsa@users.noreply.github.com>
License: MIT
Project-URL: Homepage, https://github.com/vikranth22446/llm_execution_time_predictor
Project-URL: Repository, https://github.com/vikranth22446/llm_execution_time_predictor
Project-URL: Documentation, https://github.com/vikranth22446/llm_execution_time_predictor#readme
Project-URL: Bug Tracker, https://github.com/vikranth22446/llm_execution_time_predictor/issues
Keywords: llm,inference,latency,prediction,profiling,machine-learning
Classifier: Development Status :: 4 - Beta
Classifier: Intended Audience :: Developers
Classifier: Intended Audience :: Science/Research
Classifier: License :: OSI Approved :: MIT License
Classifier: Programming Language :: Python :: 3
Classifier: Programming Language :: Python :: 3.8
Classifier: Programming Language :: Python :: 3.9
Classifier: Programming Language :: Python :: 3.10
Classifier: Programming Language :: Python :: 3.11
Classifier: Topic :: Scientific/Engineering :: Artificial Intelligence
Classifier: Topic :: Software Development :: Libraries :: Python Modules
Requires-Python: >=3.8
License-File: LICENSE
Requires-Dist: sglang
Requires-Dist: fire
Requires-Dist: gradio
Requires-Dist: numpy
Requires-Dist: matplotlib
Requires-Dist: scikit-learn
Requires-Dist: pandas
Requires-Dist: plotly
Provides-Extra: dev
Requires-Dist: pytest; extra == "dev"
Requires-Dist: black; extra == "dev"
Requires-Dist: flake8; extra == "dev"
Requires-Dist: mypy; extra == "dev"
Dynamic: license-file
